{
  "id": "7af6c148-db94-48aa-898c-158005724c55",
  "code": "KCB1",
  "name": "KCB1",
  "slug": "KCB1",
  "imgSrc": "https://thin01mstroc282prod.dxcloud.episerver.net/globalassets/items/k/kc/kcb/kcb1/13038.webp?v=2025-11-15-21-42-28",
  "images": [
    {
      "url": "https://thin01mstroc282prod.dxcloud.episerver.net/globalassets/items/k/kc/kcb/kcb1/13038.webp?v=2025-11-15-21-42-28"
    }
  ],
  "assets": [
    {
      "id": "66669ab0-c7a6-4907-ab7f-538e30ee7b1d",
      "name": "13038-E0W.pdf",
      "group": "CAD PDF",
      "description": "CAD PDF",
      "url": "https://thin01mstroc282prod.dxcloud.episerver.net/globalassets/items/k/kc/kcb/kcb1/13038-e0w.pdf?v=0116115809",
      "optiUrl": "https://media.thorlabs.com/globalassets/items/k/kc/kcb/kcb1/13038-e0w.pdf?v=0116115809",
      "mimeType": null,
      "size": 0
    },
    {
      "id": "e0b900ed-3835-49a5-8ac4-be192878f510",
      "name": "13038-E0W.dxf",
      "group": "CAD DXF",
      "description": "CAD DXF",
      "url": "https://thin01mstroc282prod.dxcloud.episerver.net/globalassets/items/k/kc/kcb/kcb1/13038-e0w.dxf?v=0116115810",
      "optiUrl": "https://media.thorlabs.com/globalassets/items/k/kc/kcb/kcb1/13038-e0w.dxf?v=0116115810",
      "mimeType": null,
      "size": 0
    },
    {
      "id": "9ec47e06-b4be-486d-aee7-a6b1b8152814",
      "name": "13038-E0W.sldprt",
      "group": "Solidworks",
      "description": "Solidworks",
      "url": "https://thin01mstroc282prod.dxcloud.episerver.net/globalassets/items/k/kc/kcb/kcb1/13038-e0w.sldprt?v=0116115810",
      "optiUrl": "https://media.thorlabs.com/globalassets/items/k/kc/kcb/kcb1/13038-e0w.sldprt?v=0116115810",
      "mimeType": null,
      "size": 0
    },
    {
      "id": "10676328-4396-4fac-8ed4-73e98bbfb956",
      "name": "13038-E0W.html",
      "group": "eDrawing / 3D Model",
      "description": "eDrawing / 3D Model",
      "url": "https://thin01mstroc282prod.dxcloud.episerver.net/globalassets/items/k/kc/kcb/kcb1/13038-e0w.html?v=0116115811",
      "optiUrl": "https://media.thorlabs.com/globalassets/items/k/kc/kcb/kcb1/13038-e0w.html?v=0116115811",
      "mimeType": null,
      "size": 0
    },
    {
      "id": "87ac1edb-704e-490a-9053-52d8fd49d096",
      "name": "13038-E0W.step",
      "group": "Step",
      "description": "Step",
      "url": "https://thin01mstroc282prod.dxcloud.episerver.net/globalassets/items/k/kc/kcb/kcb1/13038-e0w.step?v=0116115812",
      "optiUrl": "https://media.thorlabs.com/globalassets/items/k/kc/kcb/kcb1/13038-e0w.step?v=0116115812",
      "mimeType": null,
      "size": 0
    }
  ],
  "descriptionsWithFallbacksTL": [
    {
      "reviewType": "ItemUrl",
      "content": "/item/kcb1"
    },
    {
      "reviewType": "Breadcrumb",
      "content": "[[\"Right-Angle Kinematic Mirror Mounts for 30 mm Cage Systems\",\"/right-angle-kinematic-mirror-mounts-for-30-mm-cage-systems\"],[\"30 mm Cage System Optic Mounts\",\"/30-mm-cage-system-optic-mounts\"],[\"30 mm Cage Components\",\"/30-mm-cage-components\"],[\"Optical Cage Systems\",\"/optical-cage-systems\"],[\"Optomechanical Components\",\"/optomechanical-components\"],[\"Optomechanics\",\"/optomechanics\"],[\"All Products\",\"/main-visual-navigation\"],[\"KCB1\",\"/item/kcb1\"]]"
    },
    {
      "reviewType": "PerItemNoteJPY",
      "content": null
    },
    {
      "reviewType": "PerItemNoteGBP",
      "content": null
    },
    {
      "reviewType": "Title",
      "content": "Right-Angle Kinematic Mirror Mount with Tapped Cage Rod Holes, 30 mm Cage System and SM1 Compatible, 8-32 and 1/4\"-20 Mounting Holes"
    },
    {
      "reviewType": "CalibrationTerms",
      "content": null
    },
    {
      "reviewType": "PerItemNoteSEK",
      "content": null
    },
    {
      "reviewType": "PerItemNoteBRL",
      "content": null
    },
    {
      "reviewType": "PerItemNoteCNY",
      "content": null
    },
    {
      "reviewType": "CalibrationInstructions",
      "content": null
    },
    {
      "reviewType": "PerItemNoteEUR",
      "content": null
    },
    {
      "reviewType": "PerItemNote",
      "content": null
    },
    {
      "reviewType": "FamilyPageName",
      "content": "Right-Angle Kinematic Mirror Mounts for 30 mm Cage Systems"
    },
    {
      "reviewType": "FamilyPageUrl",
      "content": "/right-angle-kinematic-mirror-mounts-for-30-mm-cage-systems"
    }
  ]
}
